LICENSE.md
README.md
setup.py
src/lumensigner/__init__.py
src/lumensigner/cli.py
src/lumensigner/controller.py
src/lumensigner.egg-info/PKG-INFO
src/lumensigner.egg-info/SOURCES.txt
src/lumensigner.egg-info/dependency_links.txt
src/lumensigner.egg-info/entry_points.txt
src/lumensigner.egg-info/top_level.txt
src/lumensigner/gui/__init__.py
src/lumensigner/gui/components.py
src/lumensigner/gui/keyboard.py
src/lumensigner/gui/renderer.py
src/lumensigner/gui/screens/__init__.py
src/lumensigner/gui/screens/request_address_screens.py
src/lumensigner/gui/screens/scan_screens.py
src/lumensigner/gui/screens/screen.py
src/lumensigner/gui/screens/seed_screens.py
src/lumensigner/gui/screens/settings_screens.py
src/lumensigner/gui/screens/sign_hash_screens.py
src/lumensigner/gui/screens/sign_tx_screens.py
src/lumensigner/gui/screens/tools_screens.py
src/lumensigner/hardware/ST7789.py
src/lumensigner/hardware/__init__.py
src/lumensigner/hardware/buttons.py
src/lumensigner/hardware/camera.py
src/lumensigner/hardware/microsd.py
src/lumensigner/hardware/pivideostream.py
src/lumensigner/helpers/__init__.py
src/lumensigner/helpers/dev_tools.py
src/lumensigner/helpers/mnemonic_generation.py
src/lumensigner/helpers/qr.py
src/lumensigner/models/__init__.py
src/lumensigner/models/decode_qr.py
src/lumensigner/models/encode_qr.py
src/lumensigner/models/qr_type.py
src/lumensigner/models/seed.py
src/lumensigner/models/seed_storage.py
src/lumensigner/models/settings.py
src/lumensigner/models/settings_definition.py
src/lumensigner/models/singleton.py
src/lumensigner/models/threads.py
src/lumensigner/views/__init__.py
src/lumensigner/views/request_address.py
src/lumensigner/views/scan_views.py
src/lumensigner/views/screensaver.py
src/lumensigner/views/seed_views.py
src/lumensigner/views/settings_views.py
src/lumensigner/views/sign_hash_views.py
src/lumensigner/views/sign_tx_views.py
src/lumensigner/views/tools_views.py
src/lumensigner/views/view.py