Metadata-Version: 2.1
Name: lumensigner
Version: 0.1.0.dev2
Summary: Build an offline, airgapped Stellar signing device for less than $50!
Home-page: https://github.com/LumenSigner/lumensigner
Author: overcat
Author-email: 4catcode@gmail.com
License: UNKNOWN
Project-URL: Bug Tracker, https://github.com/LumenSigner/lumensigner/issues
Platform: UNKNOWN
Classifier: Programming Language :: Python :: 3
Classifier: License :: OSI Approved :: MIT License
Classifier: Operating System :: OS Independent
Requires-Python: >=3.7
License-File: LICENSE.md
